CHANGES.rst
LICENCE.rst
MANIFEST.in
README.rst
setup.cfg
setup.py
altered/__init__.py
altered/base.py
altered/contextdecorator.py
altered/meta.py
altered/py23compat.py
altered_states.egg-info/PKG-INFO
altered_states.egg-info/SOURCES.txt
altered_states.egg-info/dependency_links.txt
altered_states.egg-info/requires.txt
altered_states.egg-info/top_level.txt
test/test_correctness.py
test/test_expando.py
test/test_real_world.py