Metadata-Version: 1.1
Name: altered-states
Version: 1.1.0
Summary: Python monkey patching for humans.
Home-page: https://github.com/Plexical/altered.states
Author: Jacob Oscarson
Author-email: jacob@414soft.com
License: ISC
Platform: UNKNOWN
Classifier: Programming Language :: Python
Classifier: Programming Language :: Python :: 2.6
Classifier: Programming Language :: Python :: 2.7
Classifier: Development Status :: 4 - Beta
Classifier: Intended Audience :: Developers
Classifier: License :: OSI Approved :: ISC License (ISCL)
Classifier: Operating System :: OS Independent
